thulac/__init__.py
thulac/__main__.py
thulac/base/AlphaBeta.py
thulac/base/Dat.py
thulac/base/Node.py
thulac/base/WordWithTag.py
thulac/base/__init__.py
thulac/base/compatibility.py
thulac/character/CBModel.py
thulac/character/CBNGramFeature.py
thulac/character/CBTaggingDecoder.py
thulac/character/__init__.py
thulac/manage/Filter.py
thulac/manage/Postprocesser.py
thulac/manage/Preprocesser.py
thulac/manage/Punctuation.py
thulac/manage/SoExtention.py
thulac/manage/TimeWord.py
thulac/manage/__init__.py
thulac/manage/verbword.py
thulac/models/__init__.py
thulac/models/cws_dat.bin
thulac/models/cws_label.txt
thulac/models/cws_model.bin
thulac/models/idiom.dat
thulac/models/model_c_dat.bin
thulac/models/model_c_label.txt
thulac/models/model_c_model.bin
thulac/models/model_w
thulac/models/neg.dat
thulac/models/ns.dat
thulac/models/singlepun.dat
thulac/models/t2s.dat
thulac/models/time.dat
thulac/models/vD.dat
thulac/models/vM.dat
thulac/models/xu.dat
thulac-0.2.2.dist-info/METADATA
thulac-0.2.2.dist-info/WHEEL
thulac-0.2.2.dist-info/top_level.txt
thulac-0.2.2.dist-info/RECORD
